pyVTFirebase/__init__.py
pyVTFirebase/connection.py
pyVTFirebase/exceptions.py
pyVTFirebase/setup.py
pyVTFirebase/services/__init__.py
pyVTFirebase/services/auth.py
pyVTFirebase/services/helpers.py
pyVTFirebase-2021.11.9.1.dist-info/METADATA
pyVTFirebase-2021.11.9.1.dist-info/WHEEL
pyVTFirebase-2021.11.9.1.dist-info/top_level.txt
pyVTFirebase-2021.11.9.1.dist-info/RECORD
