Metadata-Version: 2.1
Name: pyVTFirebase
Version: 2021.11.9.1
Summary: A Python wrapper package for the Firebase REST API
Home-page: UNKNOWN
Author: Matthew Ashley
Author-email: matthewashley@verntechnologies.com
License: MIT
Platform: UNKNOWN
Classifier: Programming Language :: Python :: 3
Classifier: License :: OSI Approved :: MIT License
Classifier: Operating System :: OS Independent
Requires-Python: >=3.9
Requires-Dist: httpx
